omni_schema/_version.py
omni_schema/datamodel/omni_schema.py
omni_schema/schema/omni_schema.yaml
omni_schema-0.0.6.dist-info/LICENSE
omni_schema-0.0.6.dist-info/METADATA
omni_schema-0.0.6.dist-info/WHEEL
omni_schema-0.0.6.dist-info/RECORD
