Metadata-Version: 2.3
Name: omni_schema
Version: 0.0.6
Summary: Data model for omnibenchmark.
License: Apache Software License 2.0
Author: Almut Luetge
Author-email: almut.lue@gmail.com
Requires-Python: >=3.9,<4.0
Classifier: License :: Other/Proprietary License
Classifier: Programming Language :: Python :: 3
Classifier: Programming Language :: Python :: 3.9
Classifier: Programming Language :: Python :: 3.10
Classifier: Programming Language :: Python :: 3.11
Classifier: Programming Language :: Python :: 3.12
Classifier: Programming Language :: Python :: 3.13
Provides-Extra: docs
Requires-Dist: linkml-runtime (>=1.1.24,<2.0.0)
